{
  "hash": "a19c9243",
  "configHash": "e77e5129",
  "lockfileHash": "887ad8b7",
  "browserHash": "91e1ef7b",
  "optimized": {
    "react": {
      "src": "../../node_modules/react/index.js",
      "file": "react.js",
      "fileHash": "7a24ca0f",
      "needsInterop": true
    },
    "react-dom/client": {
      "src": "../../node_modules/react-dom/client.js",
      "file": "react-dom_client.js",
      "fileHash": "1154fd47",
      "needsInterop": true
    },
    "gsap": {
      "src": "../../node_modules/gsap/index.js",
      "file": "gsap.js",
      "fileHash": "bd0b9881",
      "needsInterop": false
    },
    "gsap/all": {
      "src": "../../node_modules/gsap/all.js",
      "file": "gsap_all.js",
      "fileHash": "dd090f1f",
      "needsInterop": false
    },
    "framer-motion": {
      "src": "../../node_modules/framer-motion/dist/es/index.mjs",
      "file": "framer-motion.js",
      "fileHash": "3ff87798",
      "needsInterop": false
    }
  },
  "chunks": {
    "chunk-PX2X24L7": {
      "file": "chunk-PX2X24L7.js"
    },
    "chunk-P6RTVJOB": {
      "file": "chunk-P6RTVJOB.js"
    },
    "chunk-G3PMV62Z": {
      "file": "chunk-G3PMV62Z.js"
    }
  }
}